yyx_tools/__init__.py
yyx_tools/file.py
yyx_tools/list.py
yyx_tools/utils.py
yyx_tools/video.py
yyxtools/__init__.py
yyxtools/file.py
yyxtools/list.py
yyxtools/utils.py
yyxtools/video.py
yyxutils/__init__.py
yyxutils/file.py
yyxutils/list.py
yyxutils/utils.py
yyxutils/video.py
yyxutils-0.0.1.dist-info/LICENSE
yyxutils-0.0.1.dist-info/METADATA
yyxutils-0.0.1.dist-info/WHEEL
yyxutils-0.0.1.dist-info/top_level.txt
yyxutils-0.0.1.dist-info/RECORD
